pymapgen/__init__.py
pymapgen/funcs.py
pymapgen/mersenne.py
pymapgen/render.py
pymapgen-0.1.1.dist-info/LICENSE
pymapgen-0.1.1.dist-info/METADATA
pymapgen-0.1.1.dist-info/WHEEL
pymapgen-0.1.1.dist-info/top_level.txt
pymapgen-0.1.1.dist-info/RECORD
