Metadata-Version: 2.1
Name: pymapgen
Version: 0.1.1
Summary: A package for generating data for a world with a seed.
Author: Ford2003
Author-email: tommyford28@gmail.com
Classifier: Programming Language :: Python :: 3
Classifier: License :: OSI Approved :: MIT License
Classifier: Operating System :: OS Independent
License-File: LICENSE
Requires-Dist: numpy
Requires-Dist: matplotlib
